pysheetreader.cpython-39-x86_64-linux-gnu.so
sheetreader-core/src/XlsxSheet.h
sheetreader-core/src/XlsxSheet.cpp
sheetreader-core/src/XlsxFile.cpp
sheetreader-core/src/parsing.h
sheetreader-core/src/XlsxFile.h
sheetreader-core/src/miniz/miniz.cpp
sheetreader-core/src/miniz/LICENSE
sheetreader-core/src/miniz/miniz.h
sheetreader-core/src/fast_double_parser/fast_double_parser.h
sheetreader-core/src/fast_double_parser/LICENSE
pysheetreader-0.0.1.dist-info/METADATA
pysheetreader-0.0.1.dist-info/WHEEL
pysheetreader-0.0.1.dist-info/LICENSE
pysheetreader-0.0.1.dist-info/top_level.txt
pysheetreader-0.0.1.dist-info/RECORD
