Metadata-Version: 2.1
Name: pysheetreader
Version: 0.0.1
Summary: A blazingly fast spreadsheet parser for .xlsx files
Project-URL: Homepage, https://polydbms.org
Project-URL: Repository, https://github.com/polydbms/sheetreader-python
Project-URL: Issues, https://github.com/polydbms/sheetreader-python/issues
Classifier: Programming Language :: Python :: 3
Classifier: License :: OSI Approved :: MIT License
Classifier: Operating System :: OS Independent
Requires-Python: >=3.8
License-File: LICENSE
